LICENSE
MANIFEST.in
README.md
setup.py
pointops/__init__.py
pointops/setup.py
pointops/functions/__init__.py
pointops/functions/pointops.py
pointops/src/__init__.py
pointops/src/cuda_utils.h
pointops/src/pointops_api.cpp
pointops/src/ballquery/ballquery_cuda.cpp
pointops/src/ballquery/ballquery_cuda_kernel.cu
pointops/src/ballquery/ballquery_cuda_kernel.h
pointops/src/featuredistribute/featuredistribute_cuda.cpp
pointops/src/featuredistribute/featuredistribute_cuda_kernel.cu
pointops/src/featuredistribute/featuredistribute_cuda_kernel.h
pointops/src/grouping/grouping_cuda.cpp
pointops/src/grouping/grouping_cuda_kernel.cu
pointops/src/grouping/grouping_cuda_kernel.h
pointops/src/grouping_int/grouping_int_cuda.cpp
pointops/src/grouping_int/grouping_int_cuda_kernel.cu
pointops/src/grouping_int/grouping_int_cuda_kernel.h
pointops/src/interpolation/interpolation_cuda.cpp
pointops/src/interpolation/interpolation_cuda_kernel.cu
pointops/src/interpolation/interpolation_cuda_kernel.h
pointops/src/knnquery/__init__.py
pointops/src/knnquery/knnquery_cuda.cpp
pointops/src/knnquery/knnquery_cuda_kernel.cu
pointops/src/knnquery/knnquery_cuda_kernel.h
pointops/src/knnquery_heap/__init__.py
pointops/src/knnquery_heap/knnquery_heap_cuda.cpp
pointops/src/knnquery_heap/knnquery_heap_cuda_kernel.cu
pointops/src/knnquery_heap/knnquery_heap_cuda_kernel.h
pointops/src/labelstat/labelstat_cuda.cpp
pointops/src/labelstat/labelstat_cuda_kernel.cu
pointops/src/labelstat/labelstat_cuda_kernel.h
pointops/src/sampling/sampling_cuda.cpp
pointops/src/sampling/sampling_cuda_kernel.cu
pointops/src/sampling/sampling_cuda_kernel.h
pointops_yoda.egg-info/PKG-INFO
pointops_yoda.egg-info/SOURCES.txt
pointops_yoda.egg-info/dependency_links.txt
pointops_yoda.egg-info/requires.txt
pointops_yoda.egg-info/top_level.txt